resample/__init__.py
resample/_util.py
resample/bootstrap.py
resample/empirical.py
resample/jackknife.py
resample/permutation.py
resample-1.10.1.dist-info/LICENSE
resample-1.10.1.dist-info/METADATA
resample-1.10.1.dist-info/WHEEL
resample-1.10.1.dist-info/top_level.txt
resample-1.10.1.dist-info/RECORD
